template/__init__.py
template/filters.py
template/functions.py
template-0.7.6.dist-info/LICENSE.txt
template-0.7.6.dist-info/METADATA
template-0.7.6.dist-info/WHEEL
template-0.7.6.dist-info/entry_points.txt
template-0.7.6.dist-info/top_level.txt
template-0.7.6.dist-info/RECORD
