Metadata-Version: 2.1
Name: template
Version: 0.7.6
Summary: A CLI tool for generating files from Jinja2 templates and environment variables.
Home-page: https://git.shore.co.il/nimrod/template
Author: Nimrod Adar
Author-email: nimrod@shore.co.il
License: AGPLv3+
Keywords: config configuration jinja template environment
Platform: UNKNOWN
Classifier: Development Status :: 4 - Beta
Classifier: Environment :: Console
Classifier: Intended Audience :: Developers
Classifier: Intended Audience :: Information Technology
Classifier: Intended Audience :: System Administrators
Classifier: License :: OSI Approved :: GNU Affero General Public License v3 or later (AGPLv3+)
Classifier: Programming Language :: Python :: 3
Classifier: Programming Language :: Python :: 3.6
Classifier: Programming Language :: Python :: 3.7
Classifier: Programming Language :: Python :: 3.8
Classifier: Programming Language :: Python :: 3.9
Classifier: Programming Language :: Python :: 2
Classifier: Programming Language :: Python :: 2.7
Classifier: Programming Language :: Python :: Implementation :: CPython
Classifier: Programming Language :: Python :: Implementation :: PyPy
Classifier: Topic :: Text Processing
Classifier: Topic :: Utilities
Provides-Extra: dev
Provides-Extra: jmespath
Provides-Extra: netaddr
Provides-Extra: toml
Provides-Extra: yaml
Provides-Extra: all
License-File: LICENSE.txt
